{
  "data_source": "reddit_authenticated_api",
  "generated_at_utc": "2026-05-05T23:14:19.845656+00:00",
  "top_n": 10,
  "fetch_diagnostics": {
    "subreddit": "wallstreetbets",
    "per_feed": 100,
    "auth_mode": "auto",
    "credentials_present": {
      "client_id": true,
      "client_secret": true,
      "custom_user_agent": true
    },
    "auth": {
      "attempted": true,
      "succeeded": true,
      "used": true,
      "error": null,
      "attempts": [
        {
          "attempt": 1,
          "request": "reddit_oauth_token",
          "status_code": 200,
          "outcome": "success"
        }
      ],
      "token_type": "bearer",
      "scope": "*",
      "expires_in": 86400
    },
    "feeds": [
      {
        "feed": "hot",
        "mode": "oauth",
        "status": "success",
        "items_received": 100,
        "attempts": [
          {
            "attempt": 1,
            "request": "reddit_feed:hot:oauth",
            "status_code": 200,
            "rate_limit_remaining": "999.0",
            "rate_limit_reset": "404",
            "outcome": "success"
          }
        ]
      },
      {
        "feed": "new",
        "mode": "oauth",
        "status": "success",
        "items_received": 100,
        "attempts": [
          {
            "attempt": 1,
            "request": "reddit_feed:new:oauth",
            "status_code": 200,
            "rate_limit_remaining": "998.0",
            "rate_limit_reset": "403",
            "outcome": "success"
          }
        ]
      },
      {
        "feed": "rising",
        "mode": "oauth",
        "status": "success",
        "items_received": 26,
        "attempts": [
          {
            "attempt": 1,
            "request": "reddit_feed:rising:oauth",
            "status_code": 200,
            "rate_limit_remaining": "997.0",
            "rate_limit_reset": "401",
            "outcome": "success"
          }
        ]
      },
      {
        "feed": "top",
        "mode": "oauth",
        "status": "success",
        "items_received": 100,
        "attempts": [
          {
            "attempt": 1,
            "request": "reddit_feed:top:oauth",
            "status_code": 500,
            "rate_limit_remaining": "996.0",
            "rate_limit_reset": "401",
            "outcome": "retryable_status",
            "error": "HTTP 500",
            "sleep_seconds": 2.64
          },
          {
            "attempt": 2,
            "request": "reddit_feed:top:oauth",
            "status_code": 200,
            "rate_limit_remaining": "995.0",
            "rate_limit_reset": "398",
            "outcome": "success"
          }
        ]
      }
    ],
    "used_fallback": false,
    "fallback_source": null,
    "fallback_reason": null,
    "selected_mode": "reddit_authenticated_api"
  },
  "symbols": [
    {
      "ticker": "NVDA",
      "mention_count": 13,
      "post_count": 13,
      "avg_sentiment": 0.30225384615384615,
      "total_score": 6300,
      "total_comments": 1358,
      "engagement": 122.8585930777949,
      "latest_mention": "2026-05-05 23:07:43+00:00",
      "rank_score": 65,
      "last_close": 196.5,
      "latest_rsi": 50.818079775277575,
      "latest_macd": 4.685460674074903,
      "return_5d": -0.07820048933778057,
      "return_21d": 0.1061697853814032,
      "rmse": 1.571385067080601
    },
    {
      "ticker": "AMD",
      "mention_count": 11,
      "post_count": 10,
      "avg_sentiment": -0.07272999999999999,
      "total_score": 7295,
      "total_comments": 1484,
      "engagement": 88.44305694512596,
      "latest_mention": "2026-05-05 22:06:12+00:00",
      "rank_score": 51,
      "last_close": 355.260009765625,
      "latest_rsi": 72.54333206337667,
      "latest_macd": 34.346427682215904,
      "return_5d": 0.09916159511733835,
      "return_21d": 0.6134981450778381,
      "rmse": 6.128684145455727
    },
    {
      "ticker": "INTC",
      "mention_count": 7,
      "post_count": 5,
      "avg_sentiment": 0.40843999999999997,
      "total_score": 3237,
      "total_comments": 516,
      "engagement": 54.16263037914504,
      "latest_mention": "2026-05-04 06:52:29+00:00",
      "rank_score": 27,
      "last_close": 108.1500015258789,
      "latest_rsi": 84.53084323646974,
      "latest_macd": 12.725803850442688,
      "return_5d": 0.27957886679295063,
      "return_21d": 1.1297755834128123,
      "rmse": 4.473990059447512
    },
    {
      "ticker": "MSFT",
      "mention_count": 5,
      "post_count": 5,
      "avg_sentiment": -0.11137999999999999,
      "total_score": 7213,
      "total_comments": 509,
      "engagement": 49.46443844147853,
      "latest_mention": "2026-05-05 22:26:43+00:00",
      "rank_score": 25,
      "last_close": 411.3800048828125,
      "latest_rsi": 52.58541403561456,
      "latest_macd": 6.861762366445134,
      "return_5d": -0.04163073993520672,
      "return_21d": 0.10325037410386129,
      "rmse": 9.205510836903702
    },
    {
      "ticker": "TSLA",
      "mention_count": 6,
      "post_count": 4,
      "avg_sentiment": -0.07232499999999997,
      "total_score": 1299,
      "total_comments": 503,
      "engagement": 41.012936320347265,
      "latest_mention": "2026-05-02 09:43:51+00:00",
      "rank_score": 22,
      "last_close": 389.3699951171875,
      "latest_rsi": 54.98728535849323,
      "latest_macd": 2.2091261671303073,
      "return_5d": 0.03550344793779092,
      "return_21d": 0.10359386382354918,
      "rmse": 3.2663986448205162
    },
    {
      "ticker": "GOOGL",
      "mention_count": 5,
      "post_count": 4,
      "avg_sentiment": 0.44255,
      "total_score": 946,
      "total_comments": 136,
      "engagement": 32.20796355664863,
      "latest_mention": "2026-05-05 21:46:30+00:00",
      "rank_score": 21,
      "last_close": 388.42999267578125,
      "latest_rsi": 81.33338079901655,
      "latest_macd": 19.063245647358485,
      "return_5d": 0.11049801026750994,
      "return_21d": 0.29480984472951977,
      "rmse": 3.161378331357665
    },
    {
      "ticker": "SNDK",
      "mention_count": 4,
      "post_count": 3,
      "avg_sentiment": -0.5604,
      "total_score": 3289,
      "total_comments": 905,
      "engagement": 34.10108889890034,
      "latest_mention": "2026-05-03 23:32:22+00:00",
      "rank_score": 16,
      "last_close": 1406.3199462890625,
      "latest_rsi": 81.1259207429268,
      "latest_macd": 135.2740456056937,
      "return_5d": 0.4030228767821127,
      "return_21d": 0.9407420846677377,
      "rmse": 46.92619771079528
    },
    {
      "ticker": "MSTR",
      "mention_count": 4,
      "post_count": 3,
      "avg_sentiment": 0.2764666666666667,
      "total_score": 357,
      "total_comments": 295,
      "engagement": 25.01509639248224,
      "latest_mention": "2026-05-05 16:53:51+00:00",
      "rank_score": 16,
      "last_close": 186.89999389648438,
      "latest_rsi": 68.92309186508355,
      "latest_macd": 11.24150676331152,
      "return_5d": 0.1278739142121097,
      "return_21d": 0.4637010754404842,
      "rmse": 7.004316120727222
    },
    {
      "ticker": "QQQ",
      "mention_count": 4,
      "post_count": 3,
      "avg_sentiment": -0.28806666666666664,
      "total_score": 690,
      "total_comments": 166,
      "engagement": 23.57815879997254,
      "latest_mention": "2026-05-05 22:26:43+00:00",
      "rank_score": 16,
      "last_close": 681.6099853515625,
      "latest_rsi": 76.432164730208,
      "latest_macd": 19.003182448484495,
      "return_5d": 0.03659037032203405,
      "return_21d": 0.15821577799755726,
      "rmse": 7.943892519080407
    },
    {
      "ticker": "AMZN",
      "mention_count": 3,
      "post_count": 3,
      "avg_sentiment": 0.4364333333333333,
      "total_score": 662,
      "total_comments": 172,
      "engagement": 27.32083963447218,
      "latest_mention": "2026-05-05 01:21:45+00:00",
      "rank_score": 15,
      "last_close": 273.54998779296875,
      "latest_rsi": 80.50993151109601,
      "latest_macd": 13.061985421912283,
      "return_5d": 0.05333066975328582,
      "return_21d": 0.2855397172043408,
      "rmse": 1.6828428807732914
    }
  ]
}